sphinx_ads/__init__.py
sphinx_ads/ads.py
sphinx_ads/directives/__init__.py
sphinx_ads/directives/advertisement.py
sphinx_ads/json_schema.json
sphinx_ads/json_validate.py
sphinx_ads/libs/css/sphinx_ads.css
sphinx_ads/libs/js/sphinx_ads.js
sphinx_ads/logging.py
sphinx_ads/templates/__init__.py
sphinx_ads/templates/layout.py
sphinx_ads/templates/sphinx_ads_default.html
sphinx_ads/templates/template.py
sphinx_ads/utils.py
sphinx_ads-0.0.2.dist-info/LICENSE
sphinx_ads-0.0.2.dist-info/METADATA
sphinx_ads-0.0.2.dist-info/WHEEL
sphinx_ads-0.0.2.dist-info/RECORD
