Metadata-Version: 2.1
Name: sphinx-ads
Version: 0.0.2
Summary: Sphinx extension for advertising between different Sphinx-Projects and other pages
Home-page: https://github.com/useblocks/sphinx-ads
License: MIT
Author: team useblocks
Author-email: info@useblocks.com
Maintainer: Daniel Woste
Maintainer-email: daniel@useblocks.com
Requires-Python: >=3.7.0,<4.0
Classifier: Development Status :: 2 - Pre-Alpha
Classifier: Framework :: Sphinx :: Extension
Classifier: Intended Audience :: Developers
Classifier: License :: OSI Approved :: MIT License
Classifier: Operating System :: OS Independent
Classifier: Programming Language :: Python
Classifier: Programming Language :: Python :: 3
Classifier: Programming Language :: Python :: 3.7
Classifier: Programming Language :: Python :: 3.8
Classifier: Programming Language :: Python :: 3.9
Classifier: Programming Language :: Python :: 3.10
Classifier: Programming Language :: Python :: 3.11
Classifier: Programming Language :: Python :: 3
Classifier: Programming Language :: Python :: 3.10
Classifier: Programming Language :: Python :: 3.7
Classifier: Programming Language :: Python :: 3.8
Classifier: Programming Language :: Python :: 3.9
Classifier: Topic :: Documentation :: Sphinx
Classifier: Topic :: Software Development :: Build Tools
Provides-Extra: docs
Provides-Extra: immaterial
Requires-Dist: docutils (>=0.15)
Requires-Dist: jsonschema (>3.2.0)
Requires-Dist: pathlib (>=1.0)
Requires-Dist: requests (>=2.25.1,<3.0.0)
Requires-Dist: requests-file (>=1.5.1,<2.0.0)
Requires-Dist: sphinx (>=5.0) ; extra == "docs"
Project-URL: Documentation, http://sphinx-ads.useblocks.com/
Project-URL: Repository, https://github.com/useblocks/sphinx-ads
